spacy_pattern_builder/__init__.py
spacy_pattern_builder/build.py
spacy_pattern_builder/exceptions.py
spacy_pattern_builder/match.py
spacy_pattern_builder/mutate.py
spacy_pattern_builder/util.py
test/__init__.py
test/test_spacy_pattern_builder.py
spacy_pattern_builder-0.0.7.dist-info/LICENSE
spacy_pattern_builder-0.0.7.dist-info/METADATA
spacy_pattern_builder-0.0.7.dist-info/WHEEL
spacy_pattern_builder-0.0.7.dist-info/top_level.txt
spacy_pattern_builder-0.0.7.dist-info/RECORD
