Metadata-Version: 2.1
Name: spacy-pattern-builder
Version: 0.0.7
Summary: Reverse engineer patterns for use with the SpaCy DependencyTreeMatcher
Home-page: https://github.com/cyclecycle/spacy-pattern-builder
Author: Nick Morley
Author-email: nick.morley111@gmail.com
License: MIT
Keywords: spacy-pattern-builder
Platform: UNKNOWN
Classifier: Development Status :: 2 - Pre-Alpha
Classifier: Intended Audience :: Developers
Classifier: License :: OSI Approved :: MIT License
Classifier: Natural Language :: English
Classifier: Programming Language :: Python :: 3
Classifier: Programming Language :: Python :: 3.6
Classifier: Programming Language :: Python :: Implementation :: PyPy
Requires-Dist: spacy
Requires-Dist: networkx
